neutrino_engine-5.3.3.dist-info/METADATA
neutrino_engine-5.3.3.dist-info/RECORD
neutrino_engine-5.3.3.dist-info/top_level.txt
neutrino_engine-5.3.3.dist-info/LICENSE
neutrino_engine-5.3.3.dist-info/WHEEL
neutrino/engine.cpython-38-x86_64-linux-gnu.so
neutrino/ncache.cpython-38-x86_64-linux-gnu.so
neutrino/conductor.cpython-38-x86_64-linux-gnu.so
neutrino/nlicensing.cpython-38-x86_64-linux-gnu.so
neutrino/nlogger.cpython-38-x86_64-linux-gnu.so
neutrino/composer.cpython-38-x86_64-linux-gnu.so
neutrino/job.cpython-38-x86_64-linux-gnu.so
neutrino/nexceptions.cpython-38-x86_64-linux-gnu.so
neutrino/core/__init__.cpython-38-x86_64-linux-gnu.so
neutrino/core/lgetter.cpython-38-x86_64-linux-gnu.so
neutrino/core/tools.cpython-38-x86_64-linux-gnu.so
neutrino/core/optimus/optimus.cpython-38-x86_64-linux-gnu.so
neutrino/core/optimus/fine_tuner.cpython-38-x86_64-linux-gnu.so
neutrino/core/optimus/__init__.cpython-38-x86_64-linux-gnu.so
neutrino/core/optimus/primitives/base.cpython-38-x86_64-linux-gnu.so
neutrino/core/optimus/primitives/__init__.cpython-38-x86_64-linux-gnu.so
neutrino/core/optimus/primitives/quantization.cpython-38-x86_64-linux-gnu.so
neutrino/core/optimus/primitives/_primitives.cpython-38-x86_64-linux-gnu.so
neutrino/core/transmutation/surgery.cpython-38-x86_64-linux-gnu.so
neutrino/core/transmutation/brest.cpython-38-x86_64-linux-gnu.so
neutrino/core/transmutation/precision.cpython-38-x86_64-linux-gnu.so
neutrino/core/transmutation/base.cpython-38-x86_64-linux-gnu.so
neutrino/core/transmutation/__init__.cpython-38-x86_64-linux-gnu.so
neutrino/core/transmutation/fission.cpython-38-x86_64-linux-gnu.so
neutrino/core/transmutation/fusion.cpython-38-x86_64-linux-gnu.so
neutrino/core/transmutation/cooking.cpython-38-x86_64-linux-gnu.so
neutrino/core/loop/helper.cpython-38-x86_64-linux-gnu.so
neutrino/core/loop/base_extension.cpython-38-x86_64-linux-gnu.so
neutrino/core/loop/checkpoint.cpython-38-x86_64-linux-gnu.so
neutrino/core/loop/__init__.cpython-38-x86_64-linux-gnu.so
neutrino/core/loop/extension.cpython-38-x86_64-linux-gnu.so
neutrino/core/loop/loop.cpython-38-x86_64-linux-gnu.so
