Metadata-Version: 2.1
Name: neutrino-engine
Version: 5.3.3
Summary: Deep neural network optimizer to make them faster, smaller, and energy-efficient from cloud to edge computing.
Home-page: https://www.deeplite.ai
Author: Deeplite Inc.
Author-email: support@deeplite.ai
License: Proprietary
Keywords: optimizer deep_neural_network deep_learning neural_architecture_search
Platform: Any
Classifier: Development Status :: 5 - Production/Stable
Classifier: Intended Audience :: Science/Research
Classifier: Intended Audience :: Developers
Classifier: Programming Language :: Python
Classifier: Programming Language :: Python :: 3.6
Classifier: Programming Language :: Python :: 3.7
Classifier: Programming Language :: Python :: 3.8
Classifier: Programming Language :: Python :: 3.9
Classifier: Programming Language :: Python :: Implementation :: CPython
Classifier: Topic :: Scientific/Engineering :: Artificial Intelligence
Classifier: Topic :: Software Development :: Libraries :: Python Modules
Classifier: Operating System :: POSIX :: Linux
Classifier: Natural Language :: English
Classifier: License :: Other/Proprietary License
Classifier: Environment :: Console
Requires-Dist: scipy (==1.5.4)
Requires-Dist: tensorly (==0.4.5)
Requires-Dist: pyyaml (==5.3.1)
Requires-Dist: onnx (<1.12.0,>1.7.0)
Requires-Dist: ordered-set (==4.0.2)
Requires-Dist: licensing (==0.26)
Requires-Dist: grpcio
Requires-Dist: deeplite-profiler (>=1.2.1)
Requires-Dist: deeplite-tools (>=0.0.3)
Requires-Dist: setuptools (<65.6.0)
Requires-Dist: numpy (==1.19.5)
